README.txt
setup.py
topp/__init__.py
topp.build.lib.egg-info/PKG-INFO
topp.build.lib.egg-info/SOURCES.txt
topp.build.lib.egg-info/dependency_links.txt
topp.build.lib.egg-info/entry_points.txt
topp.build.lib.egg-info/namespace_packages.txt
topp.build.lib.egg-info/not-zip-safe
topp.build.lib.egg-info/requires.txt
topp.build.lib.egg-info/top_level.txt
topp/build/__init__.py
topp/build/lib/__init__.py
topp/build/lib/base.ini
topp/build/lib/build.py
topp/build/lib/checkport.py
topp/build/lib/commands.py
topp/build/lib/create_skeleton.py
topp/build/lib/deploy.py
topp/build/lib/startup.py
topp/build/lib/taskfuncs.py
topp/build/lib/topp.build.lib.patch
topp/build/lib/utils.py
topp/build/lib/skel/setup.py.in
topp/build/lib/skel/topp/__init__.py.in
topp/build/lib/skel/topp/build/__init__.py.in
topp/build/lib/skel/topp/build/+app+/__init__.py.in
topp/build/lib/skel/topp/build/+app+/build.ini
topp/build/lib/skel/topp/build/+app+/skel/bin/+app+.rc
topp/build/lib/skel/topp/build/+app+/skel/etc/+app+.conf
topp/build/lib/skel/topp/build/+app+/skel/etc/monit.rc
