Metadata-Version: 1.0
Name: topp.build.lib
Version: 0.5.1
Summary: buildit library for topp
Home-page: http://openplans.org/
Author: The Open Planning Project
Author-email: info@openplans.org
License: GPL
Platform: UNKNOWN
